whatsapp_integration/__init__.py
whatsapp_integration/admin.py
whatsapp_integration/apps.py
whatsapp_integration/commands.py
whatsapp_integration/models.py
whatsapp_integration/serializers.py
whatsapp_integration/tasks.py
whatsapp_integration/urls.py
whatsapp_integration/utils.py
whatsapp_integration/views.py
whatsapp_integration/rate_limiter/__init__.py
whatsapp_integration/rate_limiter/lua_token_bucket.lua
whatsapp_integration/rate_limiter/lua_wrapper.py
whatsapp_integration/rate_limiter/token_bucket.py
whatsapp_integration/services/__init__.py
whatsapp_integration/services/whatsapp_service.py
whatsapp_integration-0.2.2.dist-info/licenses/LICENSE
whatsapp_integration-0.2.2.dist-info/METADATA
whatsapp_integration-0.2.2.dist-info/WHEEL
whatsapp_integration-0.2.2.dist-info/top_level.txt
whatsapp_integration-0.2.2.dist-info/RECORD
