Metadata-Version: 2.4
Name: whatsapp_integration
Version: 0.2.2
Summary: Reusable Django WhatsApp integration (Celery, rate-limiter, webhook, idempotency)
Author: OFFSIDE INTEGRATED TECHNOLOGY (Somtochukwu Emmanuel)
Author-email: offsideint@gmail.com
License: MIT
Keywords: django,whatsapp,celery,webhook
Requires-Python: >=3.8
License-File: LICENSE
Requires-Dist: Django>=3.2
Requires-Dist: requests>=2.28
Requires-Dist: celery>=5.2
Requires-Dist: redis>=4.3
Requires-Dist: psycopg2-binary>=2.9
Requires-Dist: python-dotenv>=0.21
Requires-Dist: reportlab>=4.0
Requires-Dist: djangorestframework>=3.16.1
Requires-Dist: setuptools>=80.9.0
Dynamic: license-file
